LICENSE
README.md
setup.py
VMG1312_xDSL/__init__.py
collectd_plugin_VMG1312_xDSL.egg-info/PKG-INFO
collectd_plugin_VMG1312_xDSL.egg-info/SOURCES.txt
collectd_plugin_VMG1312_xDSL.egg-info/dependency_links.txt
collectd_plugin_VMG1312_xDSL.egg-info/requires.txt
collectd_plugin_VMG1312_xDSL.egg-info/top_level.txt