Metadata-Version: 2.1
Name: collectd-plugin-VMG1312-xDSL
Version: 1.0.5
Summary: A collectd module written in Python for getting the xDSL status of Zyxel VMG1312 modems/routers
Home-page: https://github.com/kettenbach-it/collectd-plugin-VMG1312-B30A-xDSL
Author: Volker Kettenbach
Author-email: volker@ktnbch.de
License: GPL v3
Project-URL: Documentation, https://packaging.python.org/tutorials/distributing-packages
Project-URL: Source, https://github.com/kettenbach-it/collectd-plugin-VMG1312-B30A-xDSL
Keywords: Zyxel VMG1312 xDSL collectd
Platform: UNKNOWN
Classifier: Intended Audience :: System Administrators
Classifier: License :: OSI Approved :: GNU General Public License v3 (GPLv3)
Classifier: Natural Language :: English
Classifier: Operating System :: POSIX
Classifier: Programming Language :: Python
Classifier: Topic :: System :: Monitoring
License-File: LICENSE
